{
  "category1":[
    { "src": "./images/Apple.JPG", "answer": "Apple " },
    { "src": "./images/iceland.jpg", "answer": "Answer 2 for " },
    { "src": "./images/northern1.jpeg", "answer": "Answer 3 for " },
    {"src": "./images/image5.jpg", "answer": "Answer 5 for "}
  ],

  "category2":[
    { "src": "./images/logos/Youtube.JPG", "answer": "Youtube" },
    { "src": "./images/logos/whatsapp.JPG", "answer": "Whatsapp" },
    { "src": "./images/logos/Shell.JPG", "answer": "Shell" },
    { "src": "./images/logos/Toyota.JPG", "answer": "Toyota" },
    { "src": "./images/logos/Apple.JPG", "answer": "Apple" },
    { "src": "./images/logos/Mercedez.JPG", "answer": "Mercedez-Benz" },
    { "src": "./images/logos/Honda.JPG", "answer": "Honda" },
    { "src": "./images/logos/Mercycourt.JPG", "answer": "Mercy Court" },
    { "src": "./images/logos/Olympics.JPG", "answer": "Olympics" },
    { "src": "./images/logos/Wifi.JPG", "answer": "WiFi" },
    { "src": "./images/logos/bluetooth.JPG", "answer": "Bluetooth" },
    { "src": "./images/logos/Uturn.JPG", "answer": "Uturn" },
    { "src": "./images/logos/danger.JPG", "answer": "Danger" },
    { "src": "./images/logos/Buick.JPG", "answer": "Buick" },
    { "src": "./images/logos/linkedin.JPG", "answer": "Linkedin" },
    { "src": "./images/logos/Mcdonalds.JPG", "answer": "Mcdonalds " },
    { "src": "./images/logos/Playstation.JPG", "answer": "Playstation" },
    { "src": "./images/logos/Pepsi.JPG", "answer": "Pepsi" },
    { "src": "./images/logos/Suzuki.JPG", "answer": "Suzuki" },
    { "src": "./images/logos/Motorolla.JPG", "answer": "Motorolla" },
    { "src": "./images/logos/TrafficLight.JPG", "answer": "Traffic Light" },
    { "src": "./images/logos/MAYBACH.JPG", "answer": "MAYBACH" },
    { "src": "./images/logos/Dominos.JPG", "answer": "Dominos" },
    { "src": "./images/logos/Volkswagen.JPG", "answer": "Volkswagen" },
    { "src": "./images/logos/Ravens.JPG", "answer": "Baltimore Ravens" },
    { "src": "./images/logos/addidas.JPG", "answer": "addidas" },
    { "src": "./images/logos/Audi.JPG", "answer": "Audi" },
    { "src": "./images/logos/Opel.JPG", "answer": "Opel" },
    { "src": "./images/logos/Bentley.JPG", "answer": "Bentley" },
    { "src": "./images/logos/Cardillac.JPG", "answer": "Cardillac" },
    { "src": "./images/logos/Chevrolet.JPG", "answer": "Chevrolet" },
    { "src": "./images/logos/RollsRoyce.JPG", "answer": "Rolls Royce" },
    { "src": "./images/logos/Polo Ralph Lauren.JPG", "answer": "Polo Ralph Lauren" }
  ],

  "category3":[
    { "src": "./images/commonitems/antennae.JPG", "answer": "Antenna " },
    { "src": "./images/commonitems/blender.JPG", "answer": "Blender "},
    { "src": "./images/commonitems/bottleopener.JPG", "answer": "Bottle opener"},
    { "src": "./images/commonitems/Ballotbox.JPG", "answer": "Ballot box " },
    { "src": "./images/commonitems/chisel.JPG", "answer": "Chisel " },
    { "src": "./images/commonitems/bullseye.JPG", "answer": "Bull's Eye " },
    { "src": "./images/commonitems/coffeemaker.JPG", "answer": "Coffee maker " },
    { "src": "./images/commonitems/nailgun.JPG", "answer": "Nailgun" },
    { "src": "./images/commonitems/drone.JPG", "answer": "Drone"},
    { "src": "./images/commonitems/corkscew.JPG", "answer": "Corkscrew" },
    { "src": "./images/commonitems/fireextinguisher.JPG", "answer": "Fire Extinguisher "},
    { "src": "./images/commonitems/flashlight.JPG", "answer": "Flashlight" },
    { "src": "./images/commonitems/Hammer.JPG", "answer": "Hammer " },
    { "src": "./images/commonitems/hanger.JPG", "answer": "Hanger" },
    { "src": "./images/commonitems/hook.JPG", "answer": "Hook "},
    { "src": "./images/commonitems/fireplace.JPG", "answer": "Hook "},
    { "src": "./images/commonitems/handsanitizer.JPG", "answer": "Hand sanitizer"},
    { "src": "./images/commonitems/Magnifying glass.JPG", "answer": "Magnifying glass " },
    { "src": "./images/commonitems/measuringtape.JPG", "answer": "Measuring tape " },
    { "src": "./images/commonitems/megaphone.JPG", "answer": "Megaphone " },
    { "src": "./images/commonitems/oscilloscope.JPG", "answer": "Oscilloscope " },
    { "src": "./images/commonitems/padlock.JPG", "answer": "Padlock" },
    { "src": "./images/commonitems/remotecontrol.JPG", "answer": "Remote control "},
    { "src": "./images/commonitems/Router.JPG", "answer": "Router" },
    { "src": "./images/commonitems/safetygoogles.JPG", "answer": "Safety googles " },
    { "src": "./images/commonitems/Screwdriver.JPG", "answer": "Screwdriver "},
    { "src": "./images/commonitems/shovel.JPG", "answer": "Shovel " },
    { "src": "./images/commonitems/screwjack.JPG", "answer": "Screwjack " },
    { "src": "./images/commonitems/skateboard.JPG", "answer": "Skateboard"},
    { "src": "./images/commonitems/smokedetector.JPG", "answer": "Smoke detector"},
    { "src": "./images/commonitems/stapler.JPG", "answer": "Stapler" },
    { "src": "./images/commonitems/toaster.JPG", "answer": "Toaster" },
    { "src": "./images/commonitems/typewriter.JPG", "answer": "Typewriter" },
    { "src": "./images/commonitems/vendingmachine.JPG", "answer": "Vending machine " },
    { "src": "./images/commonitems/wheelbarrow.JPG", "answer": "Wheelbarrow" },
    { "src": "./images/commonitems/whisk.JPG", "answer": "Whisk"},
    { "src": "./images/commonitems/ziptie.JPG", "answer": "Ziptie" },
    { "src": "./images/commonitems/dustpan.JPG", "answer": "Dustpan " },
    { "src": "./images/commonitems/bell.JPG", "answer": "Bell "},
    { "src": "./images/commonitems/dryeraseboard.JPG", "answer": "Dry Erase Board" },
    { "src": "./images/commonitems/LED.JPG", "answer": "LED " }
  ],

  "category4":[
    { "src": "./images/compoundwords/ArrowHead.JPG", "answer": "Arrowhead " },
    { "src": "./images/compoundwords/Backlog.JPG", "answer": "Backlog " },
    { "src": "./images/compoundwords/Ballpen.JPG", "answer": "Ballpen " },
    { "src": "./images/compoundwords/BarCode.JPG", "answer": "Barcode " },
    { "src": "./images/compoundwords/Bedrock.JPG", "answer": "Bedrock" },
    { "src": "./images/compoundwords/Bellboy.JPG", "answer": "Bellboy " },
    { "src": "./images/compoundwords/Brainstorm.JPG", "answer": "Brainstorm" },
    { "src": "./images/compoundwords/ButterCup.JPG", "answer": "Buttercup" },
    { "src": "./images/compoundwords/CampFire.JPG", "answer": "Campfire" },
    { "src": "./images/compoundwords/CarPet.JPG", "answer": "Carpet" },
    { "src": "./images/compoundwords/CarPool.JPG", "answer": "Carpool" },
    { "src": "./images/compoundwords/CartWheel.JPG", "answer": "Cartwheel" },
    { "src": "./images/compoundwords/CatFish.JPG", "answer": "Catfish" },
    { "src": "./images/compoundwords/CatWalk.JPG", "answer": "Catwalk" },
    { "src": "./images/compoundwords/ChinChin.JPG", "answer": "Chinchin" },
    { "src": "./images/compoundwords/CornBread.JPG", "answer": "Cornbread" },
    { "src": "./images/compoundwords/CourtHouse.JPG", "answer": "Courthouse " },
    { "src": "./images/compoundwords/CrossRoad.JPG", "answer": "Crossroad" },
    { "src": "./images/compoundwords/cupcake.JPG", "answer": "Cupcake" },
    { "src": "./images/compoundwords/DogHouse.JPG", "answer": "Doghouse " },
    { "src": "./images/compoundwords/DoorBell.JPG", "answer": "Doorbell" },
    { "src": "./images/compoundwords/EggShell.JPG", "answer": "Eggshell" },
    { "src": "./images/compoundwords/FlowerPot.JPG", "answer": "Flowerpot " },
    { "src": "./images/compoundwords/FootBall.JPG", "answer": "Football" },
    { "src": "./images/compoundwords/Hamstring.JPG", "answer": "Hamstring" },
    { "src": "./images/compoundwords/HandBook.JPG", "answer": "Handbook " },
    { "src": "./images/compoundwords/HoneyMoon.JPG", "answer": "Honeymoon" },
    { "src": "./images/compoundwords/Keyboard.JPG", "answer": "Keyboard" },
    { "src": "./images/compoundwords/MailBox.JPG", "answer": "Mailbox " },
    { "src": "./images/compoundwords/MicroWave.JPG", "answer": "Microwave " },
    { "src": "./images/compoundwords/notebook.JPG", "answer": "Notebook" },
    { "src": "./images/compoundwords/PepperMint.JPG", "answer": "Peppermint " },
    { "src": "./images/compoundwords/PhotoGraph.JPG", "answer": "Photograph " },
    { "src": "./images/compoundwords/RainBow.JPG", "answer": "Rainbow" },
    { "src": "./images/compoundwords/RainCheck.JPG", "answer": "Raincheck " },
    { "src": "./images/compoundwords/sunflower.JPG", "answer": "Sunflower" },
    { "src": "./images/compoundwords/TableCloth.JPG", "answer": "Tablecloth" },
    { "src": "./images/compoundwords/TailGate.JPG", "answer": "Tailgate" },
    { "src": "./images/compoundwords/Toothpick.JPG", "answer": "Toothpick" },
    { "src": "./images/compoundwords/Tugboat.JPG", "answer": "Tugboat" },
    { "src": "./images/compoundwords/Watchdog.JPG", "answer": "Watchdog " },
    { "src": "./images/compoundwords/Wristband.JPG", "answer": "Wristband" },
    { "src": "./images/compoundwords/scrambledeggs.JPG", "answer": "Scrambled Eggs" },
    { "src": "./images/compoundwords/.JPG", "answer": "1Peter 5:7 " }
  ],

  "category5":[
    { "src": "./images/Food/almond.JPG", "answer": "Almond" },
    { "src": "./images/Food/bagel.JPG", "answer": "Bagel" },
    { "src": "./images/Food/beetroot.JPG", "answer": "Beetroot " },
    { "src": "./images/Food/bellpepper.JPG", "answer": "Bellpepper " },
    { "src": "./images/Food/blueberry.JPG", "answer": "Blueberry" },
    { "src": "./images/Food/brocolli.JPG", "answer": "Brocolli" },
    { "src": "./images/Food/brownie.JPG", "answer": "Brownie" },
    { "src": "./images/Food/cashew.JPG", "answer": "Cashew" },
    { "src": "./images/Food/cassava.JPG", "answer": "Cassava" },
    { "src": "./images/Food/cauliflower.JPG", "answer": "Cauliflower" },
    { "src": "./images/Food/celery.JPG", "answer": "Celery" },
    { "src": "./images/Food/clams.JPG", "answer": "Clams" },
    { "src": "./images/Food/cornbread.JPG", "answer": "Cornbread " },
    { "src": "./images/Food/cupcake.JPG", "answer": "Cupcake" },
    { "src": "./images/Food/donot.JPG", "answer": "Doughnut" },
    { "src": "./images/Food/eggplant.JPG", "answer": "Eggplant" },
    { "src": "./images/Food/frenchtoast.JPG", "answer": "Frenchtoast" },
    { "src": "./images/Food/granolabar.JPG", "answer": "Granolabar " },
    { "src": "./images/Food/guacamole.JPG", "answer": "Guacamole " },
    { "src": "./images/Food/hashbrown.JPG", "answer": "Hashbrown" },
    { "src": "./images/Food/kiwi.JPG", "answer": "Kiwi" },
    { "src": "./images/Food/mushroom.JPG", "answer": "Mushroom" },
    { "src": "./images/Food/oatmeal.JPG", "answer": "Oatmeal" },
    { "src": "./images/Food/onion.JPG", "answer": "Onion" },
    { "src": "./images/Food/peach.JPG", "answer": "Peach" },
    { "src": "./images/Food/peas.JPG", "answer": "Peas" },
    { "src": "./images/Food/popcorn.JPG", "answer": "Popcorn" },
    { "src": "./images/Food/pretzels.JPG", "answer": "Pretzels" },
    { "src": "./images/Food/pumpkin.JPG", "answer": "Pumpkin" },
    { "src": "./images/Food/salmon.JPG", "answer": "Salmon" },
    { "src": "./images/Food/salsa.JPG", "answer": "Salsa" },
    { "src": "./images/Food/sushi.JPG", "answer": "Sushi " },
    { "src": "./images/Food/suya.JPG", "answer": "Suya" },
    { "src": "./images/Food/taco.JPG", "answer": "Taco" },
    { "src": "./images/Food/trailmix.JPG", "answer": "Trailmix" },
    { "src": "./images/Food/turnip.JPG", "answer": "Turnip" },
    { "src": "./images/Food/waffles.JPG", "answer": "Waffles" },
    { "src": "./images/Food/watermelon.JPG", "answer": "Watermelon" },
    { "src": "./images/Food/zucchini.JPG", "answer": "Zucchini " },
    { "src": "./images/Food/isaiah41v10.JPG", "answer": "Answer 1C for " }

  ],
  "category6":[
    { "src": "./images/isaiah41v10.JPG", "answer": "Answer 1C for " },
    { "src": "./images/joshua1v9.JPG", "answer": "Answer 2 for " },
    { "src": "./images/psalm23v1.JPG", "answer": "Answer 3 for " },
    { "src": "./images/Exodus14v14.JPG", "answer": "Answer 4 for " },
    { "src": "./images/image5.jpg", "answer": "Answer 5 for " },
    { "src": "./images/isaiah41v10.JPG", "answer": "Answer 1C for " },
    { "src": "./images/joshua1v9.JPG", "answer": "Answer 2 for " },
    { "src": "./images/psalm23v1.JPG", "answer": "Answer 3 for " },
    { "src": "./images/Exodus14v14.JPG", "answer": "Answer 4 for " },
    { "src": "./images/image5.jpg", "answer": "Answer 5 for " },
    { "src": "./images/isaiah41v10.JPG", "answer": "Answer 1C for " },
    { "src": "./images/joshua1v9.JPG", "answer": "Answer 2 for " },
    { "src": "./images/psalm23v1.JPG", "answer": "Answer 3 for " },
    { "src": "./images/Exodus14v14.JPG", "answer": "Answer 4 for " },
    { "src": "./images/image5.jpg", "answer": "Answer 5 for " },
    { "src": "./images/isaiah41v10.JPG", "answer": "Answer 1C for " },
    { "src": "./images/joshua1v9.JPG", "answer": "Answer 2 for " },
    { "src": "./images/psalm23v1.JPG", "answer": "Answer 3 for " },
    { "src": "./images/Exodus14v14.JPG", "answer": "Answer 4 for " },
    { "src": "./images/image5.jpg", "answer": "Answer 5 for " },
    { "src": "./images/isaiah41v10.JPG", "answer": "Answer 1C for " },
    { "src": "./images/joshua1v9.JPG", "answer": "Answer 2 for " },
    { "src": "./images/psalm23v1.JPG", "answer": "Answer 3 for " },
    { "src": "./images/Exodus14v14.JPG", "answer": "Answer 4 for " },
    { "src": "./images/image5.jpg", "answer": "Answer 5 for " },
    { "src": "./images/isaiah41v10.JPG", "answer": "Answer 1C for " },
    { "src": "./images/joshua1v9.JPG", "answer": "Answer 2 for " },
    { "src": "./images/psalm23v1.JPG", "answer": "Answer 3 for " },
    { "src": "./images/Exodus14v14.JPG", "answer": "Answer 4 for " },
    { "src": "./images/image5.jpg", "answer": "Answer 5 for " },
    { "src": "./images/isaiah41v10.JPG", "answer": "Answer 1C for " },
    { "src": "./images/joshua1v9.JPG", "answer": "Answer 2 for " },
    { "src": "./images/psalm23v1.JPG", "answer": "Answer 3 for " },
    { "src": "./images/Exodus14v14.JPG", "answer": "Answer 4 for " },
    { "src": "./images/image5.jpg", "answer": "Answer 5 for " },
    { "src": "./images/isaiah41v10.JPG", "answer": "Answer 1C for " },
    { "src": "./images/joshua1v9.JPG", "answer": "Answer 2 for " },
    { "src": "./images/psalm23v1.JPG", "answer": "Answer 3 for " },
    { "src": "./images/Exodus14v14.JPG", "answer": "Answer 4 for " },
    { "src": "./images/image5.jpg", "answer": "Answer 5 for " },
    { "src": "./images/isaiah41v10.JPG", "answer": "Answer 1C for " },
    { "src": "./images/joshua1v9.JPG", "answer": "Answer 2 for " },
    { "src": "./images/psalm23v1.JPG", "answer": "Answer 3 for " },
    { "src": "./images/Exodus14v14.JPG", "answer": "Answer 4 for " },
    { "src": "./images/image5.jpg", "answer": "Answer 5 for " },
    { "src": "./images/isaiah41v10.JPG", "answer": "Answer 1C for " },
    { "src": "./images/joshua1v9.JPG", "answer": "Answer 2 for " },
    { "src": "./images/psalm23v1.JPG", "answer": "Answer 3 for " },
    { "src": "./images/Exodus14v14.JPG", "answer": "Answer 4 for " },
    { "src": "./images/image5.jpg", "answer": "Answer 5 for " },
    { "src": "./images/isaiah41v10.JPG", "answer": "Answer 1C for " },
    { "src": "./images/joshua1v9.JPG", "answer": "Answer 2 for " },
    { "src": "./images/psalm23v1.JPG", "answer": "Answer 3 for " },
    { "src": "./images/Exodus14v14.JPG", "answer": "Answer 4 for " },
    { "src": "./images/image5.jpg", "answer": "Answer 5 for " },
    {"src": "./images/image5.jpg", "answer": "Answer 5 for "}
  ],
  "category7":[
    { "src": "./images/isaiah41v10.JPG", "answer": "Answer 1C for " },
    { "src": "./images/joshua1v9.JPG", "answer": "Answer 2 for " },
    { "src": "./images/psalm23v1.JPG", "answer": "Answer 3 for " },
    { "src": "./images/Exodus14v14.JPG", "answer": "Answer 4 for " },
    { "src": "./images/image5.jpg", "answer": "Answer 5 for " },
    { "src": "./images/isaiah41v10.JPG", "answer": "Answer 1C for " },
    { "src": "./images/joshua1v9.JPG", "answer": "Answer 2 for " },
    { "src": "./images/psalm23v1.JPG", "answer": "Answer 3 for " },
    { "src": "./images/Exodus14v14.JPG", "answer": "Answer 4 for " },
    { "src": "./images/image5.jpg", "answer": "Answer 5 for " },
    { "src": "./images/isaiah41v10.JPG", "answer": "Answer 1C for " },
    { "src": "./images/joshua1v9.JPG", "answer": "Answer 2 for " },
    { "src": "./images/psalm23v1.JPG", "answer": "Answer 3 for " },
    { "src": "./images/Exodus14v14.JPG", "answer": "Answer 4 for " },
    { "src": "./images/image5.jpg", "answer": "Answer 5 for " },
    { "src": "./images/isaiah41v10.JPG", "answer": "Answer 1C for " },
    { "src": "./images/joshua1v9.JPG", "answer": "Answer 2 for " },
    { "src": "./images/psalm23v1.JPG", "answer": "Answer 3 for " },
    { "src": "./images/Exodus14v14.JPG", "answer": "Answer 4 for " },
    { "src": "./images/image5.jpg", "answer": "Answer 5 for " },
    { "src": "./images/isaiah41v10.JPG", "answer": "Answer 1C for " },
    { "src": "./images/joshua1v9.JPG", "answer": "Answer 2 for " },
    { "src": "./images/psalm23v1.JPG", "answer": "Answer 3 for " },
    { "src": "./images/Exodus14v14.JPG", "answer": "Answer 4 for " },
    { "src": "./images/image5.jpg", "answer": "Answer 5 for " },
    { "src": "./images/isaiah41v10.JPG", "answer": "Answer 1C for " },
    { "src": "./images/joshua1v9.JPG", "answer": "Answer 2 for " },
    { "src": "./images/psalm23v1.JPG", "answer": "Answer 3 for " },
    { "src": "./images/Exodus14v14.JPG", "answer": "Answer 4 for " },
    { "src": "./images/image5.jpg", "answer": "Answer 5 for " },
    { "src": "./images/isaiah41v10.JPG", "answer": "Answer 1C for " },
    { "src": "./images/joshua1v9.JPG", "answer": "Answer 2 for " },
    { "src": "./images/psalm23v1.JPG", "answer": "Answer 3 for " },
    { "src": "./images/Exodus14v14.JPG", "answer": "Answer 4 for " },
    { "src": "./images/image5.jpg", "answer": "Answer 5 for " },
    { "src": "./images/isaiah41v10.JPG", "answer": "Answer 1C for " },
    { "src": "./images/joshua1v9.JPG", "answer": "Answer 2 for " },
    { "src": "./images/psalm23v1.JPG", "answer": "Answer 3 for " },
    { "src": "./images/Exodus14v14.JPG", "answer": "Answer 4 for " },
    { "src": "./images/image5.jpg", "answer": "Answer 5 for " },
    { "src": "./images/isaiah41v10.JPG", "answer": "Answer 1C for " },
    { "src": "./images/joshua1v9.JPG", "answer": "Answer 2 for " },
    { "src": "./images/psalm23v1.JPG", "answer": "Answer 3 for " },
    { "src": "./images/Exodus14v14.JPG", "answer": "Answer 4 for " },
    { "src": "./images/image5.jpg", "answer": "Answer 5 for " },
    { "src": "./images/isaiah41v10.JPG", "answer": "Answer 1C for " },
    { "src": "./images/joshua1v9.JPG", "answer": "Answer 2 for " },
    { "src": "./images/psalm23v1.JPG", "answer": "Answer 3 for " },
    { "src": "./images/Exodus14v14.JPG", "answer": "Answer 4 for " },
    { "src": "./images/image5.jpg", "answer": "Answer 5 for " },
    {"src": "./images/image5.jpg", "answer": "Answer 5 for "}
  ],
  "category8":[
    { "src": "./images/isaiah41v10.JPG", "answer": "Answer 1C for " },
    { "src": "./images/joshua1v9.JPG", "answer": "Answer 2 for " },
    { "src": "./images/psalm23v1.JPG", "answer": "Answer 3 for " },
    { "src": "./images/Exodus14v14.JPG", "answer": "Answer 4 for " },
    { "src": "./images/image5.jpg", "answer": "Answer 5 for " },
    { "src": "./images/isaiah41v10.JPG", "answer": "Answer 1C for " },
    { "src": "./images/joshua1v9.JPG", "answer": "Answer 2 for " },
    { "src": "./images/psalm23v1.JPG", "answer": "Answer 3 for " },
    { "src": "./images/Exodus14v14.JPG", "answer": "Answer 4 for " },
    { "src": "./images/image5.jpg", "answer": "Answer 5 for " },
    { "src": "./images/isaiah41v10.JPG", "answer": "Answer 1C for " },
    { "src": "./images/joshua1v9.JPG", "answer": "Answer 2 for " },
    { "src": "./images/psalm23v1.JPG", "answer": "Answer 3 for " },
    { "src": "./images/Exodus14v14.JPG", "answer": "Answer 4 for " },
    { "src": "./images/image5.jpg", "answer": "Answer 5 for " },
    { "src": "./images/isaiah41v10.JPG", "answer": "Answer 1C for " },
    { "src": "./images/joshua1v9.JPG", "answer": "Answer 2 for " },
    { "src": "./images/psalm23v1.JPG", "answer": "Answer 3 for " },
    { "src": "./images/Exodus14v14.JPG", "answer": "Answer 4 for " },
    { "src": "./images/image5.jpg", "answer": "Answer 5 for " },
    { "src": "./images/isaiah41v10.JPG", "answer": "Answer 1C for " },
    { "src": "./images/joshua1v9.JPG", "answer": "Answer 2 for " },
    { "src": "./images/psalm23v1.JPG", "answer": "Answer 3 for " },
    { "src": "./images/Exodus14v14.JPG", "answer": "Answer 4 for " },
    { "src": "./images/image5.jpg", "answer": "Answer 5 for " },
    { "src": "./images/isaiah41v10.JPG", "answer": "Answer 1C for " },
    { "src": "./images/joshua1v9.JPG", "answer": "Answer 2 for " },
    { "src": "./images/psalm23v1.JPG", "answer": "Answer 3 for " },
    { "src": "./images/Exodus14v14.JPG", "answer": "Answer 4 for " },
    { "src": "./images/image5.jpg", "answer": "Answer 5 for " },
    { "src": "./images/isaiah41v10.JPG", "answer": "Answer 1C for " },
    { "src": "./images/joshua1v9.JPG", "answer": "Answer 2 for " },
    { "src": "./images/psalm23v1.JPG", "answer": "Answer 3 for " },
    { "src": "./images/Exodus14v14.JPG", "answer": "Answer 4 for " },
    { "src": "./images/image5.jpg", "answer": "Answer 5 for " },
    { "src": "./images/isaiah41v10.JPG", "answer": "Answer 1C for " },
    { "src": "./images/joshua1v9.JPG", "answer": "Answer 2 for " },
    { "src": "./images/psalm23v1.JPG", "answer": "Answer 3 for " },
    { "src": "./images/Exodus14v14.JPG", "answer": "Answer 4 for " },
    { "src": "./images/image5.jpg", "answer": "Answer 5 for " },
    { "src": "./images/isaiah41v10.JPG", "answer": "Answer 1C for " },
    { "src": "./images/joshua1v9.JPG", "answer": "Answer 2 for " },
    { "src": "./images/psalm23v1.JPG", "answer": "Answer 3 for " },
    { "src": "./images/Exodus14v14.JPG", "answer": "Answer 4 for " },
    { "src": "./images/image5.jpg", "answer": "Answer 5 for " },
    { "src": "./images/isaiah41v10.JPG", "answer": "Answer 1C for " },
    { "src": "./images/joshua1v9.JPG", "answer": "Answer 2 for " },
    { "src": "./images/psalm23v1.JPG", "answer": "Answer 3 for " },
    { "src": "./images/Exodus14v14.JPG", "answer": "Answer 4 for " },
    { "src": "./images/image5.jpg", "answer": "Answer 5 for " },
    { "src": "./images/isaiah41v10.JPG", "answer": "Answer 1C for " },
    { "src": "./images/joshua1v9.JPG", "answer": "Answer 2 for " },
    { "src": "./images/psalm23v1.JPG", "answer": "Answer 3 for " },
    { "src": "./images/Exodus14v14.JPG", "answer": "Answer 4 for " },
    { "src": "./images/image5.jpg", "answer": "Answer 5 for " },
    { "src": "./images/isaiah41v10.JPG", "answer": "Answer 1C for " },
    { "src": "./images/joshua1v9.JPG", "answer": "Answer 2 for " },
    { "src": "./images/psalm23v1.JPG", "answer": "Answer 3 for " },
    { "src": "./images/Exodus14v14.JPG", "answer": "Answer 4 for " },
    { "src": "./images/image5.jpg", "answer": "Answer 5 for " },
    {"src": "./images/image5.jpg", "answer": "Answer 5 for "}
  ],
  "category9":[
    { "src": "./images/isaiah41v10.JPG", "answer": "Answer 1C for " },
    { "src": "./images/joshua1v9.JPG", "answer": "Answer 2 for " },
    { "src": "./images/psalm23v1.JPG", "answer": "Answer 3 for " },
    { "src": "./images/Exodus14v14.JPG", "answer": "Answer 4 for " },
    { "src": "./images/image5.jpg", "answer": "Answer 5 for " },
    { "src": "./images/isaiah41v10.JPG", "answer": "Answer 1C for " },
    { "src": "./images/joshua1v9.JPG", "answer": "Answer 2 for " },
    { "src": "./images/psalm23v1.JPG", "answer": "Answer 3 for " },
    { "src": "./images/Exodus14v14.JPG", "answer": "Answer 4 for " },
    { "src": "./images/image5.jpg", "answer": "Answer 5 for " },
    { "src": "./images/isaiah41v10.JPG", "answer": "Answer 1C for " },
    { "src": "./images/joshua1v9.JPG", "answer": "Answer 2 for " },
    { "src": "./images/psalm23v1.JPG", "answer": "Answer 3 for " },
    { "src": "./images/Exodus14v14.JPG", "answer": "Answer 4 for " },
    { "src": "./images/image5.jpg", "answer": "Answer 5 for " },
    { "src": "./images/isaiah41v10.JPG", "answer": "Answer 1C for " },
    { "src": "./images/joshua1v9.JPG", "answer": "Answer 2 for " },
    { "src": "./images/psalm23v1.JPG", "answer": "Answer 3 for " },
    { "src": "./images/Exodus14v14.JPG", "answer": "Answer 4 for " },
    { "src": "./images/image5.jpg", "answer": "Answer 5 for " },
    { "src": "./images/isaiah41v10.JPG", "answer": "Answer 1C for " },
    { "src": "./images/joshua1v9.JPG", "answer": "Answer 2 for " },
    { "src": "./images/psalm23v1.JPG", "answer": "Answer 3 for " },
    { "src": "./images/Exodus14v14.JPG", "answer": "Answer 4 for " },
    { "src": "./images/image5.jpg", "answer": "Answer 5 for " },
    { "src": "./images/isaiah41v10.JPG", "answer": "Answer 1C for " },
    { "src": "./images/joshua1v9.JPG", "answer": "Answer 2 for " },
    { "src": "./images/psalm23v1.JPG", "answer": "Answer 3 for " },
    { "src": "./images/Exodus14v14.JPG", "answer": "Answer 4 for " },
    { "src": "./images/image5.jpg", "answer": "Answer 5 for " },
    { "src": "./images/isaiah41v10.JPG", "answer": "Answer 1C for " },
    { "src": "./images/joshua1v9.JPG", "answer": "Answer 2 for " },
    { "src": "./images/psalm23v1.JPG", "answer": "Answer 3 for " },
    { "src": "./images/Exodus14v14.JPG", "answer": "Answer 4 for " },
    { "src": "./images/image5.jpg", "answer": "Answer 5 for " },
    { "src": "./images/isaiah41v10.JPG", "answer": "Answer 1C for " },
    { "src": "./images/joshua1v9.JPG", "answer": "Answer 2 for " },
    { "src": "./images/psalm23v1.JPG", "answer": "Answer 3 for " },
    { "src": "./images/Exodus14v14.JPG", "answer": "Answer 4 for " },
    { "src": "./images/image5.jpg", "answer": "Answer 5 for " },
    { "src": "./images/isaiah41v10.JPG", "answer": "Answer 1C for " },
    { "src": "./images/joshua1v9.JPG", "answer": "Answer 2 for " },
    { "src": "./images/psalm23v1.JPG", "answer": "Answer 3 for " },
    { "src": "./images/Exodus14v14.JPG", "answer": "Answer 4 for " },
    { "src": "./images/image5.jpg", "answer": "Answer 5 for " },
    { "src": "./images/isaiah41v10.JPG", "answer": "Answer 1C for " },
    { "src": "./images/joshua1v9.JPG", "answer": "Answer 2 for " },
    { "src": "./images/psalm23v1.JPG", "answer": "Answer 3 for " },
    { "src": "./images/Exodus14v14.JPG", "answer": "Answer 4 for " },
    { "src": "./images/image5.jpg", "answer": "Answer 5 for " },
    { "src": "./images/isaiah41v10.JPG", "answer": "Answer 1C for " },
    { "src": "./images/joshua1v9.JPG", "answer": "Answer 2 for " },
    { "src": "./images/psalm23v1.JPG", "answer": "Answer 3 for " },
    { "src": "./images/Exodus14v14.JPG", "answer": "Answer 4 for " },
    { "src": "./images/image5.jpg", "answer": "Answer 5 for " },
    {"src": "./images/image5.jpg", "answer": "Answer 5 for "}
  ]

}
